{"dataURL":"file:\/\/\/Users\/dustinober\/MoonPhases\/train\/","id":"EAD78C7F-0C37-4993-B8D2-9A28B9A78317","createdDate":"2023-04-11T17:53:27Z","title":"train","modifiedDate":"2023-04-11T18:00:27Z","preferredFilename":"train","version":"1.0","dataResult":{"itemsCount":300,"createdDate":"2023-04-11T17:53:27Z","dataURL":"file:\/\/\/Users\/dustinober\/MoonPhases\/train\/","dataSourceID":"EAD78C7F-0C37-4993-B8D2-9A28B9A78317","classesCount":8,"dataAnalysis":{"summary":{"canUseValidation":1,"classCount":8,"sampleCount":300},"issues":[{"description":"8 classes found, including Waxing Gibbous Moon, Waxing Cresent Moon, Wanning Cresent Moon","severity":"debug"},{"description":"300 images found, automatically creating validation set","severity":"good"},{"description":"Smallest class is \"New Moon\" with 34 images","severity":"debug"},{"description":"Largest class is \"Waxing Gibbous Moon\" with 38 images","severity":"debug"}],"classifierAnalysis":{"labelStats":{"Waxing Cresent Moon":38,"Waxing Gibbous Moon":38,"First Quarter Moon":38,"Waning Gibbous Moon":38,"Wanning Cresent Moon":38,"Full Moon":38,"New Moon":34,"Third Quarter Moon":38}}}},"activityEntities":["dataSourceCreated",[{"id":"620634A5-A725-4AD5-8311-B31DFF9788FB","title":"Data Source Created","createdDate":"2023-04-11T17:53:27Z","event":"dataSourceCreated","subtitle":"train"}],"dataSourceTrainingStarted",[{"id":"E01352BF-8D1E-439E-A0E0-8E83AF9033C5","title":"Used By","createdDate":"2023-04-11T17:53:44Z","event":"dataSourceTrainingStarted","subtitle":"Moon Phases 1"},{"id":"EA666A81-5AC3-4056-86E3-CFFBBECA84C6","title":"Used By","createdDate":"2023-04-11T17:54:16Z","event":"dataSourceTrainingStarted","subtitle":"Moon Phases 2"},{"id":"E7F50EE1-30B0-4919-A148-20011DAD4C5B","title":"Used By","createdDate":"2023-04-11T17:54:45Z","event":"dataSourceTrainingStarted","subtitle":"Moon Phases 3"},{"id":"45BB3E76-7325-4483-ACA4-62B9F0877926","title":"Used By","createdDate":"2023-04-11T17:56:53Z","event":"dataSourceTrainingStarted","subtitle":"Moon Phases 1"},{"id":"DAC5B0F6-64D0-4A40-B798-1ECE21A72010","title":"Used By","createdDate":"2023-04-11T17:57:25Z","event":"dataSourceTrainingStarted","subtitle":"Moon Phases 1"},{"id":"0A4095F5-8CB9-4B43-AF28-703CBA2C35CC","title":"Used By","createdDate":"2023-04-11T17:58:12Z","event":"dataSourceTrainingStarted","subtitle":"Moon Phases 1"},{"id":"EEB1971A-15BA-4A42-B3DD-3B1EA2D81A89","title":"Used By","createdDate":"2023-04-11T17:59:32Z","event":"dataSourceTrainingStarted","subtitle":"Moon Phases 2"}],"dataSourceMetrics",[{"id":"013157C0-4EEC-499F-80A6-797571B81E93","title":"Data Summary","createdDate":"2023-04-11T17:53:44Z","event":"dataSourceMetrics","subtitle":"8 Classes, 300 Items"},{"id":"042E318F-8E47-423C-A60D-7660139AEB24","title":"Data Summary","createdDate":"2023-04-11T17:54:16Z","event":"dataSourceMetrics","subtitle":"8 Classes, 300 Items"},{"id":"D740316B-DCB3-4EAA-BD57-921890288856","title":"Data Summary","createdDate":"2023-04-11T17:54:45Z","event":"dataSourceMetrics","subtitle":"8 Classes, 300 Items"},{"id":"3DB0B38D-4DE7-4ECC-9F2A-49CC7DDAC892","title":"Data Summary","createdDate":"2023-04-11T17:56:53Z","event":"dataSourceMetrics","subtitle":"8 Classes, 300 Items"},{"id":"8660F2E5-220E-4520-853A-B248CCE7A8BD","title":"Data Summary","createdDate":"2023-04-11T17:57:25Z","event":"dataSourceMetrics","subtitle":"8 Classes, 300 Items"},{"id":"4D71E51F-4824-4C59-8DAE-EF78073001C5","title":"Data Summary","createdDate":"2023-04-11T17:58:12Z","event":"dataSourceMetrics","subtitle":"8 Classes, 300 Items"},{"id":"8CB0C0EF-D219-4465-9571-253A8E19382E","title":"Data Summary","createdDate":"2023-04-11T17:59:32Z","event":"dataSourceMetrics","subtitle":"8 Classes, 300 Items"}]],"pathType":0,"experimentIDs":["279E6CBB-57D0-4791-B9AA-11EE511770DC"]}