{"dataURL":"file:\/\/\/Users\/dustinober\/Downloads\/IMDB%20Dataset.csv","id":"A39356DA-EA75-40AD-907B-BF4F32C3B53A","createdDate":"2023-05-14T12:08:51Z","title":"IMDB Dataset.csv","modifiedDate":"2023-05-14T12:09:53Z","preferredFilename":"IMDB Dataset.csv","version":"1.0","dataResult":{"dataURL":"file:\/\/\/Users\/dustinober\/Downloads\/IMDB%20Dataset.csv","createdDate":"2023-05-14T12:08:51Z","dataSourceID":"A39356DA-EA75-40AD-907B-BF4F32C3B53A"},"activityEntities":["dataSourceCreated",[{"id":"BE572940-5D0C-41E4-8BDA-9CDC3E8C7D28","title":"Data Source Created","createdDate":"2023-05-14T12:08:51Z","event":"dataSourceCreated","subtitle":"IMDB Dataset.csv"}],"dataSourceTrainingStarted",[{"id":"C28BF199-3764-41F3-8FCD-AD9C4A0B58EB","title":"Used By","createdDate":"2023-05-14T12:09:53Z","event":"dataSourceTrainingStarted","subtitle":"Sentiment 1"}],"dataSourceMetrics",[{"id":"C040B6C7-DA3A-422F-9432-C96AE38BF4BA","title":"Data Summary","createdDate":"2023-05-14T12:09:53Z","event":"dataSourceMetrics","subtitle":"2 Classes, 50,000 Items"}]],"pathType":0,"experimentIDs":["C33FDE08-02B6-481A-9D41-D909CDF3B8A6"]}